{
    "packageName": "com.robotinvader.knightmare",
    "title": "Wind-up Knight",
    "description": "Wind-up Knight by Robot Invader is a high-end, action-packed, 3D side-scrolling adventure game, and it's here to show you how games are supposed to be played. \r\n\r\nGuide your Wind-up Knight through devilish levels--over 50 in all--to rescue the Princess from the clutches of the evil Black Knight. Run, jump, roll, and slash your way to victory. Not your typical runner game, Wind-up Knight is the type of challenging game you've been missing in your life. \r\n\r\nThe Princess hasn't got all day, download it now! \r\n_______________________ \r\n\r\nWind-up Knight was AppliGet's 2011 Android App of the Year!\r\n\r\n\"A success story from start to finish.\" - Tara Long, DESTRUCTOID \r\n\r\n\"4\/4 - Must Have\" - SLIDE TO PLAY\r\n\r\n\"5\/5 - Great\" - APPSPY",
    "players": [
        1
    ],
    "genres": [
        "Adventure",
        "Platformer"
    ],
    "releases": [
        {
            "name": "2.3",
            "versionCode": 0,
            "uuid": "e0bacc7f-388b-42c3-9749-4d80bb41fb4e",
            "date": "2013-07-03T01:24:16Z",
            "url": "https:\/\/archive.org\/download\/ouya_com.robotinvader.knightmare_2.3\/Wind-up%20Knight_2.3_com.robotinvader.knightmare.apk",
            "size": 50610704,
            "md5sum": null,
            "publicSize": 0,
            "nativeSize": 0
        }
    ],
    "media": {
        "discover": "http:\/\/ouya.cweiske.de\/game-images\/com.robotinvader.knightmare\/discover",
        "large": "http:\/\/ouya.cweiske.de\/game-images\/com.robotinvader.knightmare\/large",
        "video": "https:\/\/vimeo.com\/92289770",
        "screenshots": [
            "http:\/\/ouya.cweiske.de\/game-images\/com.robotinvader.knightmare\/screenshot-1",
            "http:\/\/ouya.cweiske.de\/game-images\/com.robotinvader.knightmare\/screenshot-2",
            "http:\/\/ouya.cweiske.de\/game-images\/com.robotinvader.knightmare\/screenshot-3",
            "http:\/\/ouya.cweiske.de\/game-images\/com.robotinvader.knightmare\/screenshot-4",
            "http:\/\/ouya.cweiske.de\/game-images\/com.robotinvader.knightmare\/screenshot-5"
        ],
        "details": [
            {
                "type": "video",
                "url": "https:\/\/vimeo.com\/92289770"
            },
            {
                "type": "image",
                "url": "https:\/\/www.filepicker.io\/api\/file\/7gAlG9gSJS5s1GIzIFgY\/convert?w=720",
                "thumb": "https:\/\/www.filepicker.io\/api\/file\/7gAlG9gSJS5s1GIzIFgY\/convert?w=245"
            },
            {
                "type": "image",
                "url": "https:\/\/www.filepicker.io\/api\/file\/Jov3BtffSSO0Ki8poH5w\/convert?w=720",
                "thumb": "https:\/\/www.filepicker.io\/api\/file\/Jov3BtffSSO0Ki8poH5w\/convert?w=245"
            },
            {
                "type": "image",
                "url": "https:\/\/www.filepicker.io\/api\/file\/AwPt8Y7QDWEAw7WsuMSW\/convert?w=720",
                "thumb": "https:\/\/www.filepicker.io\/api\/file\/AwPt8Y7QDWEAw7WsuMSW\/convert?w=245"
            },
            {
                "type": "image",
                "url": "https:\/\/www.filepicker.io\/api\/file\/wq2iYnF1TQef72mCGNp3\/convert?w=720",
                "thumb": "https:\/\/www.filepicker.io\/api\/file\/wq2iYnF1TQef72mCGNp3\/convert?w=245"
            },
            {
                "type": "image",
                "url": "https:\/\/www.filepicker.io\/api\/file\/DpN5BKtFRHmsOuWRIEwH\/convert?w=720",
                "thumb": "https:\/\/www.filepicker.io\/api\/file\/DpN5BKtFRHmsOuWRIEwH\/convert?w=245"
            }
        ]
    },
    "developer": {
        "uuid": null,
        "name": "Robot Invader",
        "supportEmail": "info@robotinvader.com",
        "supportPhone": null,
        "founder": false
    },
    "contentRating": "9+",
    "website": "http:\/\/robotinvader.com",
    "firstPublishedAt": "2013-07-03T01:24:16Z",
    "inAppPurchases": true,
    "overview": "Released in July 2013 by Robot Invader.",
    "premium": false,
    "rating": {
        "likeCount": 568,
        "average": 3.96,
        "count": 298
    },
    "products": [
        {
            "promoted": true,
            "identifier": "unlockallworlds",
            "name": "Wind-up Knight: Upgrade to Full Version",
            "description": "Unlocks all 52 levels in Wind-up Knight!",
            "localPrice": 7.99,
            "originalPrice": 7.99,
            "currency": "EUR"
        }
    ]
}
