{
    "packageName": "org.walawala.MoonPest",
    "title": "Moon Pest",
    "description": "Remake of an old DOS classic \"Moon Bugs\". \r\nEvil bugs are trying to steal the fuel for humanity's last space ship. Try to stop them from stealing all the barrels while the fuel is transferred to the space ship!",
    "players": [
        1
    ],
    "genres": [
        "Arcade\/Pinball",
        "Retro",
        "Short on Time?"
    ],
    "releases": [
        {
            "name": "1.5.1",
            "versionCode": 0,
            "uuid": "8bc13da6-342d-4b43-856a-d2bbf7a565b4",
            "date": "2013-12-03T07:12:22Z",
            "url": "https:\/\/archive.org\/download\/ouya_org.walawala.MoonPest_1.5.1\/Moon%20Pest_1.5.1_org.walawala.MoonPest.apk",
            "size": 4234355,
            "md5sum": null,
            "publicSize": 0,
            "nativeSize": 0
        }
    ],
    "media": {
        "discover": "http:\/\/ouya.cweiske.de\/game-images\/org.walawala.MoonPest\/discover",
        "large": "http:\/\/ouya.cweiske.de\/game-images\/org.walawala.MoonPest\/large",
        "video": null,
        "screenshots": [
            "http:\/\/ouya.cweiske.de\/game-images\/org.walawala.MoonPest\/screenshot-1",
            "http:\/\/ouya.cweiske.de\/game-images\/org.walawala.MoonPest\/screenshot-2",
            "http:\/\/ouya.cweiske.de\/game-images\/org.walawala.MoonPest\/screenshot-3",
            "http:\/\/ouya.cweiske.de\/game-images\/org.walawala.MoonPest\/screenshot-4",
            "http:\/\/ouya.cweiske.de\/game-images\/org.walawala.MoonPest\/screenshot-5"
        ],
        "details": [
            {
                "type": "image",
                "url": "https:\/\/www.filepicker.io\/api\/file\/pex38dAkSZerNFwbynLi\/convert?w=720",
                "thumb": "https:\/\/www.filepicker.io\/api\/file\/pex38dAkSZerNFwbynLi\/convert?w=245"
            },
            {
                "type": "image",
                "url": "https:\/\/www.filepicker.io\/api\/file\/5NMFcuDgSaqDxEnXfNo3\/convert?w=720",
                "thumb": "https:\/\/www.filepicker.io\/api\/file\/5NMFcuDgSaqDxEnXfNo3\/convert?w=245"
            },
            {
                "type": "image",
                "url": "https:\/\/www.filepicker.io\/api\/file\/FW87RDMQRZiTSAONyoMZ\/convert?w=720",
                "thumb": "https:\/\/www.filepicker.io\/api\/file\/FW87RDMQRZiTSAONyoMZ\/convert?w=245"
            },
            {
                "type": "image",
                "url": "https:\/\/www.filepicker.io\/api\/file\/75Av5MVSkqXxuKt5y548\/convert?w=720",
                "thumb": "https:\/\/www.filepicker.io\/api\/file\/75Av5MVSkqXxuKt5y548\/convert?w=245"
            },
            {
                "type": "image",
                "url": "https:\/\/www.filepicker.io\/api\/file\/IJvSj0wlSNiFnYDCI8ix\/convert?w=720",
                "thumb": "https:\/\/www.filepicker.io\/api\/file\/IJvSj0wlSNiFnYDCI8ix\/convert?w=245"
            }
        ]
    },
    "developer": {
        "uuid": null,
        "name": "WalaWala",
        "supportEmail": "development@walawala.org",
        "supportPhone": null,
        "founder": false
    },
    "contentRating": "9+",
    "website": "http:\/\/www.walawala.org\/blog",
    "firstPublishedAt": "2013-12-03T07:12:22Z",
    "inAppPurchases": false,
    "overview": "Released in December 2013 by WalaWala.",
    "premium": false,
    "rating": {
        "likeCount": 9,
        "average": 3.31,
        "count": 26
    }
}
