{
    "packageName": "com.gamesp.muffy",
    "title": "Muffy Boy",
    "description": "Muffy boy is an arcade platform game.Style of the best retro game Jetset Willy.Roby kid has lost all Marbles,you must collect all 80 Marbles,and Roby leave your computer.",
    "players": [
        1
    ],
    "genres": [
        "Arcade/Pinball",
        "Platformer",
        "Retro"
    ],
    "releases": [
        {
            "name": "1.01",
            "versionCode": 0,
            "uuid": "bacbcf5b-fe19-4610-adcf-1bd39baf405f",
            "date": "2014-07-18T16:29:24Z",
            "url": "https://archive.org/download/ouya_com.gamesp.muffy_1.01/Muffy%20Boy_1.01_com.gamesp.muffy.apk",
            "size": 5835898,
            "md5sum": "96501da8ca730d80d847c69da57dfb27",
            "publicSize": 3993429,
            "nativeSize": 894792,
            "cert_fingerprint": "44:80:20:02:85:BF:E8:ED:D5:79:56:CA:83:7B:4B:D8:76:CB:04:9D:1F:B1:B4:F3:35:53:C4:95:E1:44:09:A1",
            "cert_subject": "C = US, O = Android, CN = Android Debug"
        }
    ],
    "discover": "http://ouya.cweiske.de/game-images/com.gamesp.muffy/discover",
    "media": [
        {
            "type": "video",
            "url": "https://vimeo.com/100889267"
        },
        {
            "type": "image",
            "url": "http://ouya.cweiske.de/game-images/com.gamesp.muffy/detail-1",
            "thumb": "http://ouya.cweiske.de/game-images/com.gamesp.muffy/detail-1-thumb"
        },
        {
            "type": "image",
            "url": "http://ouya.cweiske.de/game-images/com.gamesp.muffy/detail-2",
            "thumb": "http://ouya.cweiske.de/game-images/com.gamesp.muffy/detail-2-thumb"
        },
        {
            "type": "image",
            "url": "http://ouya.cweiske.de/game-images/com.gamesp.muffy/detail-3",
            "thumb": "http://ouya.cweiske.de/game-images/com.gamesp.muffy/detail-3-thumb"
        },
        {
            "type": "image",
            "url": "http://ouya.cweiske.de/game-images/com.gamesp.muffy/detail-4",
            "thumb": "http://ouya.cweiske.de/game-images/com.gamesp.muffy/detail-4-thumb"
        }
    ],
    "developer": {
        "uuid": "6d331aa7-6746-4f04-9bc6-548bd0cfb4fb",
        "name": "3T Games",
        "supportEmail": "iosgames@free.fr",
        "supportPhone": null,
        "founder": false
    },
    "contentRating": "Everyone",
    "website": "http://mremakes.free.fr",
    "firstPublishedAt": "2014-07-17T17:00:08Z",
    "inAppPurchases": true,
    "overview": "Released in July 2014 by 3T Games.",
    "premium": false,
    "rating": {
        "likeCount": 0,
        "average": 2.95,
        "count": 20
    },
    "products": [
        {
            "promoted": true,
            "identifier": "muffy",
            "name": "Muffy Boy",
            "description": "",
            "localPrice": 0.99,
            "originalPrice": 0.99,
            "currency": "EUR"
        }
    ]
}
