{
    "packageName": "com.orangepixel.gunslugs",
    "title": "Gunslugs",
    "description": "Gunslugs is the most chaotic, fun, arcade action game you'll find on any platform! Non-stop action from the guys behind Meganoid, Meganoid 2 and Stardash ! \r\n\r\n“There’s so much praise I want to ramble on about, but I’ll leave it at this: Gunslugs is a game you must get your hands on” – Gamezebo\r\n\r\n\"Basically, it’s everything you could ask for from a rampaging action game, all packed up in a neat little mobile release with ample amounts of retro-style visuals, music and secrets.” – JayIsGames\r\n\r\nWe grabbed a bunch of expendable action hero's from the 80s and we made them team up as the Gunslugs to fight the war against the always evil Black Duck Army. Can you save the planet? maybe even the universe? \r\n\r\nFEATURES \r\n* Random level generation - no 2 game sessions will be the same! \r\n* Unlockable characters \r\n* Two player co-op mode is supported!\r\n* Thumping sound track \r\n* Fun variation of weapons \r\n* Tank driving! \r\n* Jetpack flying! \r\n* Secret levels \r\n* Objectives/achievements \r\n* Destruction \r\n* Chaos \r\n* Rain, snow, and big bad hell worms \r\n* Wizards, princesses, geeks, voodoo priests and many more surprises...! \r\n\r\nFor more info, check out http://orangepixel.net/gunslugs\r\n\r\n** BUGS\r\nif you run into problems or the game wont work on your device, instead of just rating 1 star, you could help us fix it by providing feedback!",
    "players": [
        1
    ],
    "genres": [
        "Arcade/Pinball",
        "FPS/Shooter",
        "Multiplayer",
        "Retro"
    ],
    "releases": [
        {
            "name": "2.0.5",
            "versionCode": 0,
            "uuid": "8a2219a8-89c4-4404-a527-18bf9063575a",
            "date": "2014-02-10T19:03:36Z",
            "url": "https://archive.org/download/ouya_com.orangepixel.gunslugs_2.0.5/Gunslugs_2.0.5_com.orangepixel.gunslugs.apk",
            "size": 6258201,
            "md5sum": "f09494aa43cfc2e03f5af9581e1dafb3",
            "publicSize": 5304026,
            "nativeSize": 0
        }
    ],
    "discover": "http://ouya.cweiske.de/game-images/com.orangepixel.gunslugs/discover",
    "media": [
        {
            "type": "video",
            "url": "https://vimeo.com/86201458"
        },
        {
            "type": "image",
            "url": "http://ouya.cweiske.de/game-images/com.orangepixel.gunslugs/screenshot-1",
            "thumb": "http://ouya.cweiske.de/game-images/com.orangepixel.gunslugs/screenshot-1-thumb"
        },
        {
            "type": "image",
            "url": "http://ouya.cweiske.de/game-images/com.orangepixel.gunslugs/screenshot-2",
            "thumb": "http://ouya.cweiske.de/game-images/com.orangepixel.gunslugs/screenshot-2-thumb"
        },
        {
            "type": "image",
            "url": "http://ouya.cweiske.de/game-images/com.orangepixel.gunslugs/screenshot-3",
            "thumb": "http://ouya.cweiske.de/game-images/com.orangepixel.gunslugs/screenshot-3-thumb"
        },
        {
            "type": "image",
            "url": "http://ouya.cweiske.de/game-images/com.orangepixel.gunslugs/screenshot-4",
            "thumb": "http://ouya.cweiske.de/game-images/com.orangepixel.gunslugs/screenshot-4-thumb"
        }
    ],
    "developer": {
        "uuid": "caa4ecd5-5936-4b9e-883c-608a70105282",
        "name": "Orangepixel",
        "supportEmail": "support@orangepixel.net",
        "supportPhone": null,
        "founder": false
    },
    "contentRating": "Everyone",
    "website": "http://orangepixel.net/gunslugs",
    "firstPublishedAt": "2013-03-20T07:34:31Z",
    "inAppPurchases": true,
    "overview": "Released in February 2014 by Orangepixel.",
    "premium": false,
    "rating": {
        "likeCount": 422,
        "average": 3.81,
        "count": 228
    },
    "products": [
        {
            "promoted": true,
            "identifier": "gunslugs_fullr",
            "name": "Gunslugs Full Version",
            "description": "",
            "localPrice": 2.99,
            "originalPrice": 2.99,
            "currency": "EUR"
        }
    ]
}
