{
    "packageName": "com.tcksoft.thrustytubes",
    "title": "Thrusty Tubes",
    "description": "Flying a spaceship is *hard*. Be gentle with the controls.\r\n\r\nTurn your ship and thrust through the tubes fighting gravity and being wary of your powerful engines.\r\n\r\nSurvive! Don't get left behind.\r\n\r\nCan you reach the moving tubes?",
    "players": [
        1
    ],
    "genres": [
        "Arcade/Pinball",
        "Retro"
    ],
    "releases": [
        {
            "name": "1.10",
            "versionCode": 0,
            "uuid": "c51000f0-77b0-4904-8bdf-30e12b3a7e0a",
            "date": "2014-03-05T20:00:05Z",
            "url": "https://archive.org/download/ouya_com.tcksoft.thrustytubes_1.10/Thrusty%20Tubes_1.10_com.tcksoft.thrustytubes.apk",
            "size": 441082,
            "md5sum": "15166a05ed81cd399a8b79579edab999",
            "publicSize": 67221,
            "nativeSize": 0,
            "cert_fingerprint": "F2:6A:0F:05:DA:AA:73:25:1D:68:5C:E5:69:B5:57:B7:48:48:ED:11:28:D7:E2:E0:87:EB:F4:FB:BD:BD:34:62",
            "cert_subject": "C = UK, ST = WF, L = Hemsworth, O = TCKSOFT, OU = TCKSOFT, CN = Andrew Pointon"
        }
    ],
    "discover": "http://ouya.cweiske.de/game-images/com.tcksoft.thrustytubes/discover",
    "media": [
        {
            "type": "image",
            "url": "http://ouya.cweiske.de/game-images/com.tcksoft.thrustytubes/screenshot-1",
            "thumb": "http://ouya.cweiske.de/game-images/com.tcksoft.thrustytubes/screenshot-1-thumb"
        },
        {
            "type": "image",
            "url": "http://ouya.cweiske.de/game-images/com.tcksoft.thrustytubes/screenshot-2",
            "thumb": "http://ouya.cweiske.de/game-images/com.tcksoft.thrustytubes/screenshot-2-thumb"
        },
        {
            "type": "image",
            "url": "http://ouya.cweiske.de/game-images/com.tcksoft.thrustytubes/screenshot-3",
            "thumb": "http://ouya.cweiske.de/game-images/com.tcksoft.thrustytubes/screenshot-3-thumb"
        },
        {
            "type": "image",
            "url": "http://ouya.cweiske.de/game-images/com.tcksoft.thrustytubes/screenshot-4",
            "thumb": "http://ouya.cweiske.de/game-images/com.tcksoft.thrustytubes/screenshot-4-thumb"
        }
    ],
    "developer": {
        "uuid": "b0d56674-9b5a-4785-a3b1-88acbd1aff69",
        "name": "TCKSOFT",
        "supportEmail": "caffeinekid@gmail.com",
        "supportPhone": null,
        "founder": false
    },
    "contentRating": "Everyone",
    "website": "http://www.tcksoft.co.uk",
    "firstPublishedAt": "2014-03-03T22:43:31Z",
    "inAppPurchases": true,
    "overview": "Released in March 2014 by TCKSOFT.",
    "premium": false,
    "rating": {
        "likeCount": 13,
        "average": 2.71,
        "count": 41
    },
    "products": [
        {
            "promoted": true,
            "identifier": "thrusty_dotate",
            "name": "It's coffee time!",
            "description": "Buy TheCaffeineKid a cup of coffee and remove the between games delay.\r\n\r\nYou will also receive a free GOLDEN SHIP.",
            "localPrice": 1.99,
            "originalPrice": 1.99,
            "currency": "EUR"
        }
    ]
}
