{
    "packageName": "com.ceruleangames.santasspecialdelivery",
    "title": "Santa's Special Delivery",
    "description": "It's Christmas Eve, and Santa is delivering presents. Gifts to good boys and girls, coal for bad boys and girls, and houses with milk and cookies? Tactical elves grab those. But then there are some people that are just so horrible, so rotten, that Santa needs to pop a squat on their chimney's and deliver his own special brand of holiday fury.\r\n\r\nSanta's Special Delivery is the holiday action arcade game you've been waiting to play! Exploding reindeer, tactical crotch-grabbing elves, a pooping minigame! Your holiday wishes have all been answered right here - Merry Christmas, one and all! (Except those of you who have been rotten... keep the toilet paper by your chimney).",
    "players": [
        1
    ],
    "genres": [
        "Arcade/Pinball",
        "Retro",
        "Short on Time?"
    ],
    "releases": [
        {
            "name": "0.52",
            "versionCode": 0,
            "uuid": "07b6a62d-ff24-4142-b136-4aeebb1b0fa6",
            "date": "2014-12-10T21:00:07Z",
            "url": "https://archive.org/download/ouya_com.ceruleangames.santasspecialdelivery_0.52/Santa_0.52_com.ceruleangames.santasspecialdelivery.apk",
            "size": 78877450,
            "md5sum": "64918bbe2680a56b65531b659910155f",
            "publicSize": 196573,
            "nativeSize": 14992732,
            "cert_fingerprint": "28:27:E7:F7:58:78:7A:86:46:33:04:F5:09:BA:48:B9:76:2D:AE:3A:23:2A:52:48:4D:0C:D8:5A:DA:22:02:D4",
            "cert_subject": "C = US, O = Android, CN = Android Debug"
        }
    ],
    "discover": "http://ouya.cweiske.de/game-images/com.ceruleangames.santasspecialdelivery/discover",
    "media": [
        {
            "type": "video",
            "url": "http://vimeo.com/113781741"
        },
        {
            "type": "image",
            "url": "http://ouya.cweiske.de/game-images/com.ceruleangames.santasspecialdelivery/detail-1",
            "thumb": "http://ouya.cweiske.de/game-images/com.ceruleangames.santasspecialdelivery/detail-1-thumb"
        },
        {
            "type": "image",
            "url": "http://ouya.cweiske.de/game-images/com.ceruleangames.santasspecialdelivery/detail-2",
            "thumb": "http://ouya.cweiske.de/game-images/com.ceruleangames.santasspecialdelivery/detail-2-thumb"
        },
        {
            "type": "image",
            "url": "http://ouya.cweiske.de/game-images/com.ceruleangames.santasspecialdelivery/detail-3",
            "thumb": "http://ouya.cweiske.de/game-images/com.ceruleangames.santasspecialdelivery/detail-3-thumb"
        },
        {
            "type": "image",
            "url": "http://ouya.cweiske.de/game-images/com.ceruleangames.santasspecialdelivery/detail-4",
            "thumb": "http://ouya.cweiske.de/game-images/com.ceruleangames.santasspecialdelivery/detail-4-thumb"
        }
    ],
    "developer": {
        "uuid": "11111111-e4f1-4e29-9aae-fb887df96037",
        "name": "Cerulean Games, Inc.",
        "supportEmail": null,
        "supportPhone": null,
        "founder": false
    },
    "contentRating": "17+",
    "website": "http://www.CeruleanGames.com/",
    "firstPublishedAt": "2014-12-10T21:00:07Z",
    "inAppPurchases": false,
    "overview": "Released in December 2014 by Cerulean Games, Inc..",
    "premium": true,
    "rating": {
        "likeCount": 0,
        "average": 4.2,
        "count": 25
    },
    "products": [
        {
            "promoted": true,
            "identifier": "SantaDelivery",
            "name": "Santa's Special Delivery",
            "description": "It's Christmas eve, and Santa has to deliver gifts, coal, tactical elves and... a pooping minigame? What's going on here!?",
            "localPrice": 1.99,
            "originalPrice": 1.99,
            "currency": "USD"
        }
    ]
}
