{
    "packageName": "com.jenots.dummytown",
    "title": "Dummy Town",
    "description": "Control crash dummies, brought back to life by radiation, smashing their way through the debris of the forsaken town, used for nuclear bomb tests, running away from yet another explosion, in hopes to save their lives (or so they think).\r\n\r\nDummy Town is a strategy like action game, controlling up to 5 characters simultaneously, trying to get them to a safe zone through punching, jump kicking and exploding obstacles on their way, while empowering their abilities with radioactively charged amulets.\r\n\r\nControl up to 5 characters\r\nSmashing, jump kicking and exploding obstacles\r\nAnd using radioactive amulets\r\nAll to get them to a save zone\r\n\r\nNew Version:\r\nFixed switching amulets\r\nAdded support for multiple controllers (Xbox, PS3, Amazon, Moga, etc)",
    "players": [
        1
    ],
    "genres": [
        "Adventure",
        "Short on Time?"
    ],
    "releases": [
        {
            "name": "1.1",
            "versionCode": 0,
            "uuid": "a23c311e-0304-4fad-8b30-2928a945bc74",
            "date": "2014-08-20T09:17:37Z",
            "url": "https://archive.org/download/ouya_com.jenots.dummytown_1.1/DummyTown_1.1_com.jenots.dummytown.apk",
            "size": 17795126,
            "md5sum": "b4c2cf0dd1ccfe071293e75e4e14bb35",
            "publicSize": 535997,
            "nativeSize": 5994496,
            "cert_fingerprint": "61:C5:17:32:24:10:2C:98:FB:9D:40:73:74:05:25:7F:8F:83:1A:11:55:E4:0D:02:6D:2F:E8:7B:E5:7F:05:52",
            "cert_subject": "C = RU, ST = Moscow, L = Russia, O = jenots.com, OU = jenots.com, CN = julia"
        }
    ],
    "discover": "http://ouya.cweiske.de/game-images/com.jenots.dummytown/discover",
    "media": [
        {
            "type": "image",
            "url": "http://ouya.cweiske.de/game-images/com.jenots.dummytown/detail-1",
            "thumb": "http://ouya.cweiske.de/game-images/com.jenots.dummytown/detail-1-thumb"
        },
        {
            "type": "image",
            "url": "http://ouya.cweiske.de/game-images/com.jenots.dummytown/detail-2",
            "thumb": "http://ouya.cweiske.de/game-images/com.jenots.dummytown/detail-2-thumb"
        },
        {
            "type": "image",
            "url": "http://ouya.cweiske.de/game-images/com.jenots.dummytown/detail-3",
            "thumb": "http://ouya.cweiske.de/game-images/com.jenots.dummytown/detail-3-thumb"
        },
        {
            "type": "image",
            "url": "http://ouya.cweiske.de/game-images/com.jenots.dummytown/detail-4",
            "thumb": "http://ouya.cweiske.de/game-images/com.jenots.dummytown/detail-4-thumb"
        },
        {
            "type": "image",
            "url": "http://ouya.cweiske.de/game-images/com.jenots.dummytown/detail-5",
            "thumb": "http://ouya.cweiske.de/game-images/com.jenots.dummytown/detail-5-thumb"
        }
    ],
    "developer": {
        "uuid": "bbab3a03-0dff-48fb-97db-ec3e8cd9a6f9",
        "name": "JenotsCom",
        "supportEmail": "contact@jenots.com",
        "alternateEmail": "jenotsapps@gmail.com",
        "supportPhone": null,
        "founder": false
    },
    "contentRating": "9+",
    "website": "http://jenots.com/dummy-town",
    "firstPublishedAt": "2014-05-14T19:26:54Z",
    "inAppPurchases": false,
    "overview": "Released in August 2014 by JenotsCom.",
    "premium": false,
    "rating": {
        "likeCount": 0,
        "average": 3,
        "count": 43
    }
}
