{
    "packageName": "com.ph4labs.crackingtiles",
    "title": "Cracking Tiles",
    "description": "The floor you are walking over is breaking one tile after the other.. Compete with your friends and try to stay alive the longest!\n\nMULTIPLAYER 2-4 PLAYERS.\nWARNING! VERY ADDICTIVE.\n\n-=-=(  Made in Uppsala by PH4 Labs  )=-=-",
    "players": [
        2,
        3,
        4
    ],
    "genres": [
        "Arcade/Pinball",
        "Multiplayer",
        "Racing",
        "Retro",
        "Short on Time?"
    ],
    "releases": [
        {
            "name": "1.02",
            "versionCode": 0,
            "uuid": "5e6a1c27-d400-4858-9688-0a4675cab1ac",
            "date": "2015-09-30T17:33:29Z",
            "url": "https://archive.org/download/ouya_com.ph4labs.crackingtiles_1.02/Cracking%20Tiles_1.02_com.ph4labs.crackingtiles.apk",
            "size": 4455363,
            "md5sum": "2b8214045f635b4edf078162a043b0bc",
            "publicSize": 3859814,
            "nativeSize": 567248,
            "cert_fingerprint": "90:C3:0E:64:97:14:DB:13:D4:B0:C2:F0:2F:32:1A:6C:72:9D:4E:C5:9B:7E:11:47:BE:73:49:2F:80:15:B0:40",
            "cert_subject": "C = US, O = Android, CN = Android Debug"
        }
    ],
    "discover": "http://ouya.cweiske.de/game-images/com.ph4labs.crackingtiles/discover",
    "media": [
        {
            "type": "image",
            "url": "http://ouya.cweiske.de/game-images/com.ph4labs.crackingtiles/detail-1",
            "thumb": "http://ouya.cweiske.de/game-images/com.ph4labs.crackingtiles/detail-1-thumb"
        },
        {
            "type": "image",
            "url": "http://ouya.cweiske.de/game-images/com.ph4labs.crackingtiles/detail-2",
            "thumb": "http://ouya.cweiske.de/game-images/com.ph4labs.crackingtiles/detail-2-thumb"
        },
        {
            "type": "image",
            "url": "http://ouya.cweiske.de/game-images/com.ph4labs.crackingtiles/detail-3",
            "thumb": "http://ouya.cweiske.de/game-images/com.ph4labs.crackingtiles/detail-3-thumb"
        }
    ],
    "developer": {
        "uuid": "1bd84927-a5e5-4e29-a6a4-b1fe646d9cd8",
        "name": "PH4 Labs",
        "supportEmail": null,
        "supportPhone": null,
        "founder": true
    },
    "contentRating": "Everyone",
    "website": "http://www.ph4labs.com",
    "firstPublishedAt": "2015-09-30T17:33:29Z",
    "inAppPurchases": true,
    "overview": "Released in September 2015 by PH4 Labs.",
    "premium": false,
    "rating": {
        "likeCount": 0,
        "average": 3.4,
        "count": 10
    }
}
