{
    "packageName": "de.blubberquark.frozenbullet",
    "title": "Frozen Bullet",
    "description": "Frozen Bullet is a simultaneous turn-based tactics platformer for two players. When you create your strategy, you can rewind time to revise fine-tune your plan.\r\n\r\nFrozen Bullet features four game modes, seven unit types and over ten purchasable hats.",
    "players": [
        2
    ],
    "genres": [
        "Multiplayer",
        "Platformer",
        "Sim/Strategy"
    ],
    "releases": [
        {
            "name": "0.1.8",
            "versionCode": 0,
            "uuid": "f192c599-19c4-4e1c-a991-07b428499175",
            "date": "2014-11-15T08:06:42Z",
            "url": "https://archive.org/download/ouya_de.blubberquark.frozenbullet_0.1.8/Frozen%20Bullet_0.1.8_de.blubberquark.frozenbullet.apk",
            "size": 11866675,
            "md5sum": "1023794eddf21f96aaa6607df8d1f4dc",
            "publicSize": 107734,
            "nativeSize": 3671272,
            "cert_fingerprint": "0D:02:21:E8:2E:72:0A:EE:A1:F4:11:BA:C2:E7:68:3C:D0:88:30:13:BA:EC:1F:A8:1B:94:4B:C5:3C:58:14:8D",
            "cert_subject": "CN = Robert Pfeiffer"
        }
    ],
    "discover": "http://ouya.cweiske.de/game-images/de.blubberquark.frozenbullet/discover",
    "media": [
        {
            "type": "image",
            "url": "http://ouya.cweiske.de/game-images/de.blubberquark.frozenbullet/detail-1",
            "thumb": "http://ouya.cweiske.de/game-images/de.blubberquark.frozenbullet/detail-1-thumb"
        },
        {
            "type": "image",
            "url": "http://ouya.cweiske.de/game-images/de.blubberquark.frozenbullet/detail-2",
            "thumb": "http://ouya.cweiske.de/game-images/de.blubberquark.frozenbullet/detail-2-thumb"
        },
        {
            "type": "image",
            "url": "http://ouya.cweiske.de/game-images/de.blubberquark.frozenbullet/detail-3",
            "thumb": "http://ouya.cweiske.de/game-images/de.blubberquark.frozenbullet/detail-3-thumb"
        }
    ],
    "developer": {
        "uuid": "d73675e6-1720-469d-aa85-50d8c0b9dc96",
        "name": "Blubberquark Software",
        "supportEmail": "bob@blubberquark.de",
        "supportPhone": null,
        "founder": false
    },
    "contentRating": "9+",
    "website": null,
    "firstPublishedAt": "2014-11-07T09:46:23Z",
    "inAppPurchases": true,
    "overview": "Released in November 2014 by Blubberquark Software.",
    "premium": false,
    "rating": {
        "likeCount": 0,
        "average": 3.05,
        "count": 38
    }
}
