{
    "packageName": "io.arkeus.Antichromatic",
    "title": "Antichromatic",
    "description": "Use the power of the chromatic armor to swap between two dimensions as you explore the facility in an attempt to find the source of the fracture that split the world in two. Warning: The difficulty of this game is very high.",
    "players": [
        1
    ],
    "genres": [
        "Adventure",
        "Platformer",
        "Puzzle/Trivia"
    ],
    "releases": [
        {
            "name": "1.0.0",
            "versionCode": 0,
            "uuid": "173eb47f-9846-4ab0-bcef-e3369324a10f",
            "date": "2013-07-15T22:04:46Z",
            "url": "https://archive.org/download/ouya_io.arkeus.Antichromatic_1.0.0/Antichromatic_1.0.0_io.arkeus.Antichromatic.apk",
            "size": 13592312,
            "md5sum": "780f8530ab17573a0a8be01847f57b60",
            "publicSize": 0,
            "nativeSize": 0,
            "cert_fingerprint": "79:0F:A8:55:B4:F1:EF:D8:FB:E5:F4:BB:5D:BF:A3:4E:C4:C3:14:EB:75:72:B7:E1:8D:07:99:74:CA:8E:17:30",
            "cert_subject": "C = US, O = , OU = , CN = Lee Miller"
        }
    ],
    "discover": "http://ouya.cweiske.de/game-images/io.arkeus.Antichromatic/discover",
    "media": [
        {
            "type": "image",
            "url": "https://archive.org/download/ouya_io.arkeus.Antichromatic_1.0.0/w4l1RGcZQGKdJbMKsqJW.jpg",
            "thumb": "https://archive.org/download/ouya_io.arkeus.Antichromatic_1.0.0/w4l1RGcZQGKdJbMKsqJW_thumb.jpg"
        },
        {
            "type": "image",
            "url": "https://archive.org/download/ouya_io.arkeus.Antichromatic_1.0.0/r4e3rmzT7S9SIpgbBjet.jpg",
            "thumb": "https://archive.org/download/ouya_io.arkeus.Antichromatic_1.0.0/r4e3rmzT7S9SIpgbBjet_thumb.jpg"
        },
        {
            "type": "image",
            "url": "https://archive.org/download/ouya_io.arkeus.Antichromatic_1.0.0/hJ19NT4CTEKBaIWy7ksK.jpg",
            "thumb": "https://archive.org/download/ouya_io.arkeus.Antichromatic_1.0.0/hJ19NT4CTEKBaIWy7ksK_thumb.jpg"
        },
        {
            "type": "image",
            "url": "https://archive.org/download/ouya_io.arkeus.Antichromatic_1.0.0/QFNziQZaSL1Er3A4wANU.jpg",
            "thumb": "https://archive.org/download/ouya_io.arkeus.Antichromatic_1.0.0/QFNziQZaSL1Er3A4wANU_thumb.jpg"
        }
    ],
    "developer": {
        "uuid": "02947534-badf-4377-bcfe-0a054f650266",
        "name": "Lee Miller",
        "supportEmail": "iarkeus@gmail.com",
        "supportPhone": null,
        "founder": true
    },
    "contentRating": "9+",
    "website": "http://arkeus.io",
    "firstPublishedAt": "2013-07-15T22:04:46Z",
    "inAppPurchases": false,
    "overview": "Released in July 2013 by Lee Miller.",
    "premium": false,
    "rating": {
        "likeCount": 373,
        "average": 4.26,
        "count": 410
    }
}
