{
    "packageName": "raft.jumpy.android.ouya",
    "title": "Sky Maze 3D",
    "description": "Dodge the traps, find your way and guide the ball to exit. A fun and challenging action game.\r\n\r\n- Cool 3D effects, beautiful graphics and sound\r\n- Scoreloop leaderboard\r\n- 9 different tile types\r\n- 12 free total 50 challenging levels",
    "players": [
        1
    ],
    "genres": [
        "Kids List",
        "Platformer"
    ],
    "releases": [
        {
            "name": "1.32",
            "versionCode": 0,
            "uuid": "7fad30a5-c86e-4e9e-bbc9-496e7510ce54",
            "date": "2013-10-26T18:17:48Z",
            "url": "https://archive.org/download/ouya_raft.jumpy.android.ouya_1.32/Sky%20Maze%203D_1.32_raft.jumpy.android.ouya.apk",
            "size": 14387086,
            "md5sum": "2244677cabfc75bde8e41a00a1a9cfb0",
            "publicSize": 0,
            "nativeSize": 0,
            "cert_fingerprint": "6F:85:B6:94:3D:D8:99:47:F7:F8:43:79:99:94:21:C1:57:2C:4B:D6:64:9C:CC:24:CA:E7:C9:C1:D6:D3:FE:27",
            "cert_subject": "C = TR, ST = Unknown, L = Istanbul, O = Karga Mobile, OU = Unknown, CN = Hakan Eryargi"
        },
        {
            "name": "1.31",
            "versionCode": 14,
            "uuid": "4307ab4f-6163-4d4f-8625-7a2d6940bd54",
            "date": "2013-10-26T00:00:00Z",
            "url": "https://archive.org/download/ouya_raft.jumpy.android.ouya_1.31/Sky%20Maze%203D_1.31_raft.jumpy.android.ouya.apk",
            "size": 14389232,
            "md5sum": "e56216edab827db07ee0f52744419cc5",
            "cert_fingerprint": "6F:85:B6:94:3D:D8:99:47:F7:F8:43:79:99:94:21:C1:57:2C:4B:D6:64:9C:CC:24:CA:E7:C9:C1:D6:D3:FE:27",
            "cert_subject": "C = TR, ST = Unknown, L = Istanbul, O = Karga Mobile, OU = Unknown, CN = Hakan Eryargi"
        }
    ],
    "discover": "http://ouya.cweiske.de/game-images/raft.jumpy.android.ouya/discover",
    "media": [
        {
            "type": "video",
            "url": "https://vimeo.com/77445071"
        },
        {
            "type": "image",
            "url": "http://ouya.cweiske.de/game-images/raft.jumpy.android.ouya/screenshot-1",
            "thumb": "http://ouya.cweiske.de/game-images/raft.jumpy.android.ouya/screenshot-1-thumb"
        },
        {
            "type": "image",
            "url": "http://ouya.cweiske.de/game-images/raft.jumpy.android.ouya/screenshot-2",
            "thumb": "http://ouya.cweiske.de/game-images/raft.jumpy.android.ouya/screenshot-2-thumb"
        },
        {
            "type": "image",
            "url": "http://ouya.cweiske.de/game-images/raft.jumpy.android.ouya/screenshot-3",
            "thumb": "http://ouya.cweiske.de/game-images/raft.jumpy.android.ouya/screenshot-3-thumb"
        },
        {
            "type": "image",
            "url": "http://ouya.cweiske.de/game-images/raft.jumpy.android.ouya/screenshot-4",
            "thumb": "http://ouya.cweiske.de/game-images/raft.jumpy.android.ouya/screenshot-4-thumb"
        },
        {
            "type": "image",
            "url": "http://ouya.cweiske.de/game-images/raft.jumpy.android.ouya/screenshot-5",
            "thumb": "http://ouya.cweiske.de/game-images/raft.jumpy.android.ouya/screenshot-5-thumb"
        },
        {
            "type": "image",
            "url": "http://ouya.cweiske.de/game-images/raft.jumpy.android.ouya/screenshot-6",
            "thumb": "http://ouya.cweiske.de/game-images/raft.jumpy.android.ouya/screenshot-6-thumb"
        },
        {
            "type": "image",
            "url": "http://ouya.cweiske.de/game-images/raft.jumpy.android.ouya/screenshot-7",
            "thumb": "http://ouya.cweiske.de/game-images/raft.jumpy.android.ouya/screenshot-7-thumb"
        },
        {
            "type": "image",
            "url": "http://ouya.cweiske.de/game-images/raft.jumpy.android.ouya/screenshot-8",
            "thumb": "http://ouya.cweiske.de/game-images/raft.jumpy.android.ouya/screenshot-8-thumb"
        }
    ],
    "developer": {
        "uuid": "381e826e-fe0f-4d3f-b1c9-7d2be1794c40",
        "name": "Karga Games",
        "supportEmail": "mobile@aptalkarga.com",
        "supportPhone": null,
        "founder": false
    },
    "contentRating": "Everyone",
    "website": "http://www.aptalkarga.com/mobile",
    "firstPublishedAt": "2013-03-24T21:41:26Z",
    "inAppPurchases": true,
    "overview": "Released in October 2013 by Karga Games.",
    "premium": false,
    "rating": {
        "likeCount": 36,
        "average": 3.41,
        "count": 59
    }
}
