{
    "packageName": "com.freelunchdesign.icytowerclassic.launcher",
    "title": "Icy Tower (Launcher)",
    "description": "*** 40 MILLION PLAYERS CAN'T BE\r\nWRONG! ***\r\nThe #1 jumping game of all time: IcyTower!\r\n\r\nHelp Harold jump up the tower. Perform amazing combos without falling down.\r\nCan you make it to the top?",
    "players": [
        1
    ],
    "genres": [
        "Arcade/Pinball",
        "Launcher",
        "PlayJam GameStick"
    ],
    "releases": [
        {
            "name": "1.0",
            "versionCode": 1,
            "uuid": "cf8de614-f49f-448a-8bbb-798456bba5ea",
            "date": "2025-11-22T17:13:53Z",
            "url": "http://ouya.cweiske.de/apks/gamestick/com.freelunchdesign.icytowerclassic/com.freelunchdesign.icytowerclassic.launcher-1.apk",
            "size": 98780,
            "md5sum": "d0590d7bd5afd5813397ba54b88d5592",
            "cert_fingerprint": "A3:81:0C:7A:E7:20:11:83:33:F6:8C:55:F4:9C:D4:14:5F:D4:A0:2E:C0:11:27:F8:CC:62:56:D6:A5:07:F4:1A",
            "cert_subject": "C=AT, OU=CEO, CN=Andreas St."
        }
    ],
    "discover": "http://ouya.cweiske.de/apks/gamestick/com.freelunchdesign.icytowerclassic/discover",
    "media": [
        {
            "type": "image",
            "url": "http://ouya.cweiske.de/apks/gamestick/com.freelunchdesign.icytowerclassic/screen1.jpg"
        },
        {
            "type": "image",
            "url": "http://ouya.cweiske.de/apks/gamestick/com.freelunchdesign.icytowerclassic/screen2.jpg"
        },
        {
            "type": "image",
            "url": "http://ouya.cweiske.de/apks/gamestick/com.freelunchdesign.icytowerclassic/screen3.jpg"
        }
    ],
    "developer": {
        "uuid": "11111111-2590-4f1f-b4ad-7a3ea00edfd6",
        "name": "Andiweli"
    },
    "contentRating": "Everyone",
    "website": null,
    "firstPublishedAt": "2013-07-05",
    "inAppPurchases": false,
    "premium": true,
    "relationships": {
        "original": "com.freelunchdesign.icytowerclassic"
    }
}
